codetracer_python_recorder-0.2.0.dist-info/METADATA
codetracer_python_recorder-0.2.0.dist-info/WHEEL
codetracer_python_recorder-0.2.0.dist-info/entry_points.txt
codetracer_python_recorder-0.2.0.dist-info/licenses/LICENSE
codetracer_python_recorder/.gitignore
codetracer_python_recorder/__init__.py
codetracer_python_recorder/__main__.py
codetracer_python_recorder/api.py
codetracer_python_recorder/auto_start.py
codetracer_python_recorder/cli.py
codetracer_python_recorder/codetracer_python_recorder.cpython-313-darwin.so
codetracer_python_recorder/formats.py
codetracer_python_recorder/session.py
codetracer_python_recorder-0.2.0.dist-info/RECORD
