Metadata-Version: 2.4
Name: codetracer-python-recorder
Version: 0.2.0
Classifier: Development Status :: 4 - Beta
Classifier: Intended Audience :: Developers
Classifier: License :: OSI Approved :: MIT License
Classifier: Programming Language :: Python :: 3
Classifier: Programming Language :: Python :: 3 :: Only
Classifier: Programming Language :: Python :: Implementation :: CPython
Classifier: Programming Language :: Python :: 3.12
Classifier: Programming Language :: Python :: 3.13
Classifier: Programming Language :: Rust
Classifier: Operating System :: Microsoft :: Windows
Classifier: Operating System :: MacOS
Classifier: Operating System :: POSIX :: Linux
Classifier: Topic :: Software Development :: Debuggers
License-File: LICENSE
Summary: Low-level Rust-backed Python module for CodeTracer recording (PyO3)
Author: Metacraft Labs Ltd
Requires-Python: >=3.12, <3.14
Project-URL: Homepage, https://github.com/metacraft-labs/codetracer-python-recorder/tree/main/codetracer-python-recorder
Project-URL: Repository, https://github.com/metacraft-labs/codetracer-python-recorder
Project-URL: Issues, https://github.com/metacraft-labs/codetracer-python-recorder/issues
Project-URL: Changelog, https://github.com/metacraft-labs/codetracer-python-recorder/releases
